gcm/__init__.py
gcm/gcm.py
gcm_syn-1.2.0.dist-info/licenses/LICENSE
tests/__init__.py
tests/test_gcm.py
gcm_syn-1.2.0.dist-info/METADATA
gcm_syn-1.2.0.dist-info/WHEEL
gcm_syn-1.2.0.dist-info/top_level.txt
gcm_syn-1.2.0.dist-info/RECORD
