Metadata-Version: 2.4
Name: gcm-syn
Version: 1.2.0
Summary: A package for generating synthetic data with preserved correlation structures.
Author: Jens E. d'Hondt
Author-email: "Jens E. d'Hondt" <jensdhondt7@gmail.com>
License-Expression: GPL-3.0-or-later
Project-URL: Homepage, https://github.com/JdHondt/gcm
Classifier: Programming Language :: Python :: 3
Classifier: Operating System :: OS Independent
Requires-Python: >=3.7
License-File: LICENSE
Requires-Dist: numpy
Requires-Dist: scipy
Provides-Extra: test
Requires-Dist: pytest>=6.0; extra == "test"
Requires-Dist: pytest-cov>=2.0; extra == "test"
Provides-Extra: dev
Requires-Dist: pytest>=6.0; extra == "dev"
Requires-Dist: pytest-cov>=2.0; extra == "dev"
Requires-Dist: black; extra == "dev"
Requires-Dist: flake8; extra == "dev"
Dynamic: author
Dynamic: license-file
